{"id_": "1053182133731233793", "raw_data": {"created_at": "Fri Oct 19 07:12:42 +0000 2018", "id": 1053182133731233793, "id_str": "1053182133731233793", "full_text": "Teaching a lesson last week in a cave in #Afghanistan for a group of refugee children who had no access to state education, the cave was in the mountains. I was able to provide them with writing pads, books, pens and some basic resources. #RunningDangerously https://t.co/FONon0lbdm", "truncated": false, "display_text_range": [0, 258], "entities": {"hashtags": [{"text": "Afghanistan", "indices": [41, 53]}, {"text": "RunningDangerously", "indices": [239, 258]}], "symbols": [], "user_mentions": [], "urls": [], "media": [{"id": 1053182117218320385, "id_str": "1053182117218320385", "indices": [259, 282], "media_url": "http://pbs.twimg.com/media/Dp2njjyXgAEMJje.jpg", "media_url_https": "https://pbs.twimg.com/media/Dp2njjyXgAEMJje.jpg", "url": "https://t.co/FONon0lbdm", "display_url": "pic.twitter.com/FONon0lbdm", "expanded_url": "https://twitter.com/mrjordanwylie/status/1053182133731233793/photo/1", "type": "photo", "original_info": {"width": 2048, "height": 1152, "focus_rects": [{"x": 0, "y": 5, "h": 1147, "w": 2048}, {"x": 294, "y": 0, "h": 1152, "w": 1152}, {"x": 365, "y": 0, "h": 1152, "w": 1011}, {"x": 582, "y": 0, "h": 1152, "w": 576}, {"x": 0, "y": 0, "h": 1152, "w": 2048}]}, "sizes": {"thumb": {"w": 150, "h": 150, "resize": "crop"}, "medium": {"w": 1200, "h": 675, "resize": "fit"}, "large": {"w": 2048, "h": 1152, "resize": "fit"}, "small": {"w": 680, "h": 383, "resize": "fit"}}}]}, "extended_entities": {"media": [{"id": 1053182117218320385, "id_str": "1053182117218320385", "indices": [259, 282], "media_url": "http://pbs.twimg.com/media/Dp2njjyXgAEMJje.jpg", "media_url_https": "https://pbs.twimg.com/media/Dp2njjyXgAEMJje.jpg", "url": "https://t.co/FONon0lbdm", "display_url": "pic.twitter.com/FONon0lbdm", "expanded_url": "https://twitter.com/mrjordanwylie/status/1053182133731233793/photo/1", "type": "photo", "original_info": {"width": 2048, "height": 1152, "focus_rects": [{"x": 0, "y": 5, "h": 1147, "w": 2048}, {"x": 294, "y": 0, "h": 1152, "w": 1152}, {"x": 365, "y": 0, "h": 1152, "w": 1011}, {"x": 582, "y": 0, "h": 1152, "w": 576}, {"x": 0, "y": 0, "h": 1152, "w": 2048}]}, "sizes": {"thumb": {"w": 150, "h": 150, "resize": "crop"}, "medium": {"w": 1200, "h": 675, "resize": "fit"}, "large": {"w": 2048, "h": 1152, "resize": "fit"}, "small": {"w": 680, "h": 383, "resize": "fit"}}, "media_key": "3_1053182117218320385", "ext_alt_text": null, "ext_media_availability": {"status": "available"}, "ext_media_color": {"palette": [{"rgb": {"red": 197, "green": 197, "blue": 199}, "percentage": 48.44}, {"rgb": {"red": 55, "green": 50, "blue": 46}, "percentage": 17.33}, {"rgb": {"red": 150, "green": 119, "blue": 92}, "percentage": 7.75}, {"rgb": {"red": 177, "green": 95, "blue": 49}, "percentage": 3.72}, {"rgb": {"red": 42, "green": 48, "blue": 74}, "percentage": 3.17}]}, "ext": {"mediaStats": {"r": "Missing", "ttl": -1}}}]}, "source": "<a href=\"http://twitter.com/download/iphone\" rel=\"nofollow\">Twitter for iPhone</a>", "in_reply_to_status_id": null, "in_reply_to_status_id_str": null, "in_reply_to_user_id": null, "in_reply_to_user_id_str": null, "in_reply_to_screen_name": null, "user_id": 812447905156136960, "user_id_str": "812447905156136960", "geo": null, "coordinates": null, "place": null, "contributors": null, "is_quote_status": false, "retweet_count": 13, "favorite_count": 82, "reply_count": 3, "quote_count": 1, "conversation_id": 1053182133731233793, "conversation_id_str": "1053182133731233793", "favorited": false, "retweeted": false, "possibly_sensitive": false, "possibly_sensitive_editable": true, "lang": "en", "supplemental_language": null}}