{"id_": "1139794763207462913", "raw_data": {"created_at": "Sat Jun 15 07:20:22 +0000 2019", "id": 1139794763207462913, "id_str": "1139794763207462913", "full_text": "Located in Bhogal, the Sayed Jamalludin Afghan High School is being run by a samaritan to help the children of Afghan refugees to negotiate their displacement through some very constructive means. With some assistance that it receives from the MoE, Afghanistan @Mirwaisbalkhi1 ...", "truncated": false, "display_text_range": [0, 280], "entities": {"hashtags": [], "symbols": [], "user_mentions": [{"screen_name": "Mirwaisbalkhi1", "name": "Mirwais Balkhi", "id": 1048800753324888065, "id_str": "1048800753324888065", "indices": [261, 276]}], "urls": []}, "source": "<a href=\"http://twitter.com/download/android\" rel=\"nofollow\">Twitter for Android</a>", "in_reply_to_status_id": 1139794760665665536, "in_reply_to_status_id_str": "1139794760665665536", "in_reply_to_user_id": 903099016488951808, "in_reply_to_user_id_str": "903099016488951808", "in_reply_to_screen_name": "mobilemigrant", "user_id": 903099016488951808, "user_id_str": "903099016488951808", "geo": null, "coordinates": null, "place": null, "contributors": null, "is_quote_status": false, "retweet_count": 0, "favorite_count": 0, "reply_count": 1, "quote_count": 0, "conversation_id": 1139794760665665536, "conversation_id_str": "1139794760665665536", "favorited": false, "retweeted": false, "lang": "en", "supplemental_language": null, "self_thread": {"id": 1139794760665665536, "id_str": "1139794760665665536"}}}