{"id_": "1217354258435264512", "raw_data": {"created_at": "Wed Jan 15 07:54:07 +0000 2020", "id": 1217354258435264512, "id_str": "1217354258435264512", "full_text": "Violence.\nDisplacement.\nDrought.\n\nDespite these barriers to learning, children in Afghanistan are grasping the opportunity to learn, and with it, finding a sense of normality in their lives.\n\nUNICEF Afghanistan https://t.co/JW0ddYckXb", "truncated": false, "display_text_range": [0, 234], "entities": {"hashtags": [], "symbols": [], "user_mentions": [], "urls": [{"url": "https://t.co/JW0ddYckXb", "expanded_url": "https://www.facebook.com/100008547373010/posts/2328561570772066/", "display_url": "facebook.com/10000854737301…", "indices": [211, 234]}]}, "source": "<a href=\"http://www.facebook.com/twitter\" rel=\"nofollow\">Facebook</a>", "in_reply_to_status_id": null, "in_reply_to_status_id_str": null, "in_reply_to_user_id": null, "in_reply_to_user_id_str": null, "in_reply_to_screen_name": null, "user_id": 5981342, "user_id_str": "5981342", "geo": null, "coordinates": null, "place": null, "contributors": null, "is_quote_status": false, "retweet_count": 1, "favorite_count": 0, "reply_count": 0, "quote_count": 0, "conversation_id": 1217354258435264512, "conversation_id_str": "1217354258435264512", "favorited": false, "retweeted": false, "possibly_sensitive": false, "possibly_sensitive_editable": true, "lang": "en", "supplemental_language": null}}